README.md
setup.cfg
setup.py
binomial_gauss_distributions/Binomialdistribution.py
binomial_gauss_distributions/Gaussiandistribution.py
binomial_gauss_distributions/Generaldistribution.py
binomial_gauss_distributions/__init__.py
binomial_gauss_distributions.egg-info/PKG-INFO
binomial_gauss_distributions.egg-info/SOURCES.txt
binomial_gauss_distributions.egg-info/dependency_links.txt
binomial_gauss_distributions.egg-info/not-zip-safe
binomial_gauss_distributions.egg-info/top_level.txt